hw01/__init__.py
hw01/constants.py
hw01/hw01.py
hw01-1.0.0.dist-info/METADATA
hw01-1.0.0.dist-info/RECORD
hw01-1.0.0.dist-info/WHEEL
hw01-1.0.0.dist-info/top_level.txt
