Metadata-Version: 2.1
Name: hw01
Version: 1.0.0
Summary: Python library to work with Lenovo HW01
Home-page: https://github.com/nabilbendafi/hw01
Author: Nabil BENDAFI
Author-email: nabil@bendafi.fr
License: MIT
Keywords: api health
Platform: UNKNOWN
Classifier: Programming Language :: Python :: 3
Classifier: License :: OSI Approved :: MIT License
Classifier: Operating System :: OS Independent
Requires-Dist: bluepy
